iko.py
iko-0.4.0.dist-info/LICENSE
iko-0.4.0.dist-info/METADATA
iko-0.4.0.dist-info/WHEEL
iko-0.4.0.dist-info/top_level.txt
iko-0.4.0.dist-info/RECORD
