Metadata-Version: 2.1
Name: iko
Version: 0.4.0
Summary: Iko is an asynchronous micro-framework for converting data into different structures.
Home-page: UNKNOWN
Author: Ilya Chistyakov, Pavel Polyakov
Author-email: ilchistyakov@gmail.com, pollydrag@yandex.ru
License: MIT
Project-URL: Source, https://github.com/MyGodIsHe/iko
Platform: UNKNOWN
Classifier: Development Status :: 3 - Alpha
Classifier: Intended Audience :: Developers
Classifier: License :: OSI Approved :: MIT License
Classifier: Programming Language :: Python :: 3
Classifier: Programming Language :: Python :: 3.6
Classifier: Programming Language :: Python :: 3.7
Classifier: Programming Language :: Python :: 3.8
Requires-Python: >=3.6
